LICENSE
MANIFEST.in
README.rst
setup.cfg
setup.py
django_hpo.egg-info/PKG-INFO
django_hpo.egg-info/SOURCES.txt
django_hpo.egg-info/dependency_links.txt
django_hpo.egg-info/requires.txt
django_hpo.egg-info/top_level.txt
hpo/__init__.py
hpo/admin.py
hpo/api.py
hpo/apps.py
hpo/forms.py
hpo/models.py
hpo/tests.py
hpo/urls.py
hpo/views.py
hpo/management/commands/import_hpo.py
hpo/migrations/0001_initial.py
hpo/migrations/0002_auto_20211021_1524.py
hpo/migrations/0003_auto_20211021_1525.py
hpo/migrations/0004_phenotype_top_parent.py
hpo/migrations/__init__.py
hpo/static/js/hpo.js
hpo/templates/hpo/widgets/attrs.html
hpo/templates/hpo/widgets/phenotype.html
hpo/templates/hpo/widgets/phenotype_multiple.html